conversation_qa/__init__.py
conversation_qa/qa.py
conversation_qa/upload_to_hf.py
conversation_qa/utils.py
conversation_qa-0.0.18.dist-info/METADATA
conversation_qa-0.0.18.dist-info/WHEEL
conversation_qa-0.0.18.dist-info/top_level.txt
conversation_qa-0.0.18.dist-info/RECORD
