Metadata-Version: 2.1
Name: conversation-qa
Version: 0.0.18
Summary: Conversational QA.
Home-page: http://github.com/fractalego/conversation_qa
Author: Alberto Cetoli
Author-email: alberto@fractalego.io
License: UNKNOWN
Platform: UNKNOWN
Classifier: License :: OSI Approved :: MIT License
Requires-Dist: transformers (>=4.17.0)
Requires-Dist: sentence-transformers (>=2.0.0)
Requires-Dist: torch (>=1.12.1)
